beancount_capitalone/__init__.py
beancount_capitalone/credit.py
beancount_capitalone/credit_test.py
beancount_capitalone-0.1.1.dist-info/LICENSE
beancount_capitalone-0.1.1.dist-info/METADATA
beancount_capitalone-0.1.1.dist-info/WHEEL
beancount_capitalone-0.1.1.dist-info/top_level.txt
beancount_capitalone-0.1.1.dist-info/RECORD
