Metadata-Version: 2.1
Name: beancount-capitalone
Version: 0.1.1
Summary: Import CapitalOne banking transactions into beancount format
Home-page: https://github.com/mtlynch/beancount-capitalone.git
Author: Michael Lynch
License: MIT
Keywords: capitalone beancount bookkeeping finance
Platform: UNKNOWN
Requires-Python: >=3.9
